tarvis/atb/__init__.py
tarvis/atb/advancedtradingbot.py
tarvis/atb/atbs.py
tarvis/atb/exchangeaccount.py
tarvis_atb-0.9.14.dist-info/LICENSE.txt
tarvis_atb-0.9.14.dist-info/METADATA
tarvis_atb-0.9.14.dist-info/WHEEL
tarvis_atb-0.9.14.dist-info/top_level.txt
tarvis_atb-0.9.14.dist-info/RECORD
