Metadata-Version: 2.1
Name: tarvis-atb
Version: 0.9.14
Summary: Tarvis Advanced Trading Bot Library
Home-page: https://tarvislabs.com/
Author: Tarvis Labs
Author-email: python@tarvislabs.com
License: MIT
Platform: UNKNOWN
Classifier: License :: OSI Approved :: MIT License
Requires-Python: >=3.10
License-File: LICENSE.txt
Requires-Dist: tarvis-common (==0.9.14)
